LICENSE.txt
README.md
pyproject.toml
setup.py
src/dj_deploy.egg-info/PKG-INFO
src/dj_deploy.egg-info/SOURCES.txt
src/dj_deploy.egg-info/dependency_links.txt
src/dj_deploy.egg-info/entry_points.txt
src/dj_deploy.egg-info/requires.txt
src/dj_deploy.egg-info/top_level.txt
src/djdeploy/__init__.py
src/djdeploy/index.py